datasette_no_truncate/__init__.py
datasette_no_truncate-0.1.dist-info/LICENSE
datasette_no_truncate-0.1.dist-info/METADATA
datasette_no_truncate-0.1.dist-info/WHEEL
datasette_no_truncate-0.1.dist-info/entry_points.txt
datasette_no_truncate-0.1.dist-info/top_level.txt
datasette_no_truncate-0.1.dist-info/RECORD
