Metadata-Version: 2.1
Name: datasette-no-truncate
Version: 0.1
Summary: Tiny Datasette plugin to disable text truncation in table displays
Home-page: https://github.com/simonw/datasette-no-truncate
Author: Simon Willison
License: Apache License, Version 2.0
Project-URL: Issues, https://github.com/simonw/datasette-no-truncate/issues
Project-URL: CI, https://github.com/simonw/datasette-no-truncate/actions
Project-URL: Changelog, https://github.com/simonw/datasette-no-truncate/releases
Classifier: Framework :: Datasette
Classifier: License :: OSI Approved :: Apache Software License
Requires-Python: >=3.7
License-File: LICENSE
Requires-Dist: datasette
Provides-Extra: test
Requires-Dist: pytest ; extra == 'test'
Requires-Dist: pytest-asyncio ; extra == 'test'
